turbowriter/__init__.py
turbowriter/util/__init__.py
turbowriter-0.4.4.dist-info/LICENSE
turbowriter-0.4.4.dist-info/METADATA
turbowriter-0.4.4.dist-info/WHEEL
turbowriter-0.4.4.dist-info/top_level.txt
turbowriter-0.4.4.dist-info/RECORD
