Metadata-Version: 2.2
Name: turbowriter
Version: 0.4.4
Summary: A small example package
Author-email: Robert Degen <turbodev@mailbox.org>
Project-URL: Homepage, https://github.com/turbo-bert
Project-URL: Issues, https://github.com/turbo-bert
Classifier: Programming Language :: Python :: 3
Classifier: License :: OSI Approved :: MIT License
Classifier: Operating System :: OS Independent
Requires-Python: >=3.8
License-File: LICENSE
Requires-Dist: Pillow
Requires-Dist: qrcode
Requires-Dist: reportlab
Requires-Dist: tabulate
